util_agent/__init__.py
util_agent/_info.py
util_agent/_log.py
util_agent/agent_examples.py
util_agent/agent_factory.py
util_agent/agent_validator.py
util_agent/ark.py
util_agent/azure_openai.py
util_agent/openai.py
util_agent/py.typed
util_agent/settings.py
util_agent/vertex.py
util_agent-0.0.1.dist-info/METADATA
util_agent-0.0.1.dist-info/WHEEL
util_agent-0.0.1.dist-info/top_level.txt
util_agent-0.0.1.dist-info/RECORD
