Metadata-Version: 2.4
Name: util_agent
Version: 0.0.1
Summary: ...
Author-email: Sheldon Lee <sheldonlee@outlook.com>
Classifier: Programming Language :: Python :: 3
Classifier: Operating System :: OS Independent
Requires-Python: >=3.10
Provides-Extra: dev
Requires-Dist: pip; extra == "dev"
Requires-Dist: twine; extra == "dev"
Requires-Dist: build; extra == "dev"
Requires-Dist: pytest; extra == "dev"
Requires-Dist: mypy; extra == "dev"
Requires-Dist: types-toml; extra == "dev"
Requires-Dist: pre-commit; extra == "dev"
Requires-Dist: pytest-asyncio; extra == "dev"
